MANIFEST.in
README.md
README.rst
setup.cfg
setup.py
yucc/__init__.py
yucc/cli.py
yucc/config.py
yucc/logger.py
yucc/util.py
yucc/commands/__init__.py
yucc/commands/account.py
yucc/commands/command_base.py
yucc/commands/plans.py
yucc/commands/profile.py
yucc/commands/servers.py
yucc/commands/tags.py
yucc/commands/templates.py
yucc/commands/zones.py