Metadata-Version: 1.0
Name: yucc
Version: 0.8.3
Summary: CLI for UpCloud public cloud service
Home-page: UNKNOWN
Author: Erik Sørensen
Author-email: erik@enssoftware.no
License: MIT
Keywords: cli upcloud
Platform: UNKNOWN
